src/__init__.py
src/sentences.py
src/words.py
pywc-0.0.1.dist-info/LICENSE
pywc-0.0.1.dist-info/METADATA
pywc-0.0.1.dist-info/WHEEL
pywc-0.0.1.dist-info/top_level.txt
pywc-0.0.1.dist-info/RECORD
